dtwentyCommunications/Communications.py
dtwentyCommunications/Exceptions.py
dtwentyCommunications/__init__.py
dtwentyCommunications/__version__.py
d20_communications-0.0.4.dist-info/LICENSE
d20_communications-0.0.4.dist-info/METADATA
d20_communications-0.0.4.dist-info/WHEEL
d20_communications-0.0.4.dist-info/top_level.txt
d20_communications-0.0.4.dist-info/RECORD
