Metadata-Version: 2.1
Name: d20-communications
Version: 0.0.4
Summary: A small ORM for multimodel DBs
Home-page: https://github.com/d20services/python_arango_communications_module
Author: Alex Sánchez Vega
Author-email: alex@d20.services
Project-URL: Bug Tracker, https://github.com/d20services/python_arango_communications_module/issues
Classifier: Programming Language :: Python :: 3
Classifier: License :: OSI Approved :: MIT License
Classifier: Operating System :: OS Independent
Requires-Python: >=3.8
License-File: LICENSE
Requires-Dist: pyArango
Requires-Dist: datetime
Requires-Dist: d20-orm
Requires-Dist: requests
Requires-Dist: sendgrid
Requires-Dist: exponent-server-sdk
Requires-Dist: Twilio
